pyventure/__init__.py
pyventure/game_loops.py
pyventure/items.py
pyventure/message.py
pyventure/place.py
pyventure/player.py
pyventure/save.py
pyventure/user_answer.py
pyventure-0.1.1.dist-info/WHEEL
pyventure-0.1.1.dist-info/METADATA
pyventure-0.1.1.dist-info/RECORD
