Metadata-Version: 2.1
Name: pyventure
Version: 0.1.1
Summary: A simple framework for creating text adventure games.
Home-page: https://github.com/d-flood/pyventure
License: MIT
Author: David Flood
Author-email: davidfloodii@gmail.com
Requires-Python: >=3.10,<4.0
Classifier: License :: OSI Approved :: MIT License
Classifier: Programming Language :: Python :: 3
Classifier: Programming Language :: Python :: 3.10
Requires-Dist: rich (>=12.4.4,<13.0.0)
Project-URL: Repository, https://github.com/d-flood/pyventure
